tbtamr/Annotate.py
tbtamr/Call.py
tbtamr/CustomLog.py
tbtamr/Parse.py
tbtamr/Predict.py
tbtamr/Search.py
tbtamr/Utils.py
tbtamr/__init__.py
tbtamr/tbtamr.py
tbtamr/version.py
tbtamr/configs/classification_criteria.csv
tbtamr/configs/db_config.json
tbtamr/configs/interpretation_criteria.csv
tbtamr/db/tbtamr.barcode.bed
tbtamr/db/tbtamr.fasta
tbtamr/db/who_v2_catalog.csv
tbtamr/tests/__init__.py
tbtamr/tests/conftest.py
tbtamr/tests/test_tbtamr.py
tbtamr-1.0.3.dist-info/LICENSE
tbtamr-1.0.3.dist-info/METADATA
tbtamr-1.0.3.dist-info/WHEEL
tbtamr-1.0.3.dist-info/entry_points.txt
tbtamr-1.0.3.dist-info/top_level.txt
tbtamr-1.0.3.dist-info/RECORD
