Metadata-Version: 2.1
Name: tbtamr
Version: 1.0.3
Summary: Running TB-Profiler for MDU
Home-page: https://github.com/MDU-PHL/tbtamr
Author: Kristy Horan
Author-email: kristyhoran15@gmail.com
Maintainer: Kristy Horan
Maintainer-email: kristyhoran15@gmail.com
Classifier: Development Status :: 4 - Beta
Classifier: Programming Language :: Python :: Implementation :: CPython
Classifier: Intended Audience :: Science/Research
Classifier: License :: OSI Approved :: GNU General Public License v3 (GPLv3)
Classifier: Natural Language :: English
Classifier: Programming Language :: Python :: 3 :: Only
Classifier: Programming Language :: Python :: 3.10
Classifier: Topic :: Scientific/Engineering :: Bio-Informatics
Requires-Python: >=3.10, <4
License-File: LICENSE
Requires-Dist: pandas
Requires-Dist: pytest
Requires-Dist: tabulate
Requires-Dist: unidecode
Requires-Dist: pysam
Requires-Dist: requests
Requires-Dist: joblib
Requires-Dist: pydantic
Requires-Dist: tqdm
